[
  {
    "scale_name": "Million Scale (1%)",
    "n_neurons": 1000000,
    "n_active_per_area": 10000,
    "n_areas": 5,
    "sparsity": 0.99,
    "memory_gb": 14.689453125,
    "steps_per_sec": 72.93116173384385,
    "ms_per_step": 13.711560000228928,
    "neurons_per_sec": 72931161.73384385,
    "active_per_sec": 3646558.0866921926,
    "gpu_memory_used_gb": 14.689453125,
    "gpu_memory_available_gb": 15.99169921875,
    "gpu_memory_utilization": 91.85673719886415,
    "cpu_memory_used_gb": 25.278778076171875,
    "cpu_memory_available_gb": 31.419132232666016,
    "cpu_memory_utilization": 80.45663988736742,
    "theoretical_memory_gb": 0.005122274160385132,
    "memory_efficiency": 0.6,
    "cache_hit_rate": 0.0,
    "memory_pool_efficiency": 0.0
  },
  {
    "scale_name": "Ten Million Scale (1%)",
    "n_neurons": 10000000,
    "n_active_per_area": 100000,
    "n_areas": 5,
    "sparsity": 0.99,
    "memory_gb": 14.681640625,
    "steps_per_sec": 290.17468519428854,
    "ms_per_step": 3.4461999995983206,
    "neurons_per_sec": 2901746851.9428854,
    "active_per_sec": 145087342.59714428,
    "gpu_memory_used_gb": 14.681640625,
    "gpu_memory_available_gb": 15.99169921875,
    "gpu_memory_utilization": 91.8078837287411,
    "cpu_memory_used_gb": 25.27960968017578,
    "cpu_memory_available_gb": 31.419132232666016,
    "cpu_memory_utilization": 80.45928669504417,
    "theoretical_memory_gb": 0.42002648115158087,
    "memory_efficiency": 0.6,
    "cache_hit_rate": 0.0,
    "memory_pool_efficiency": 0.0
  },
  {
    "scale_name": "Hundred Million Scale (0.1%)",
    "n_neurons": 100000000,
    "n_active_per_area": 100000,
    "n_areas": 5,
    "sparsity": 0.999,
    "memory_gb": 14.681640625,
    "steps_per_sec": 375.5840332724427,
    "ms_per_step": 2.6625199992849957,
    "neurons_per_sec": 37558403327.24427,
    "active_per_sec": 187792016.63622135,
    "gpu_memory_used_gb": 14.681640625,
    "gpu_memory_available_gb": 15.99169921875,
    "gpu_memory_utilization": 91.8078837287411,
    "cpu_memory_used_gb": 25.279560089111328,
    "cpu_memory_available_gb": 31.419132232666016,
    "cpu_memory_utilization": 80.45912885788913,
    "theoretical_memory_gb": 0.42002648115158087,
    "memory_efficiency": 0.06,
    "cache_hit_rate": 0.0,
    "memory_pool_efficiency": 0.0
  },
  {
    "scale_name": "Billion Scale (0.01%)",
    "n_neurons": 1000000000,
    "n_active_per_area": 100000,
    "n_areas": 5,
    "sparsity": 0.9999,
    "memory_gb": 14.681640625,
    "steps_per_sec": 155.13496741824432,
    "ms_per_step": 6.446000000141794,
    "neurons_per_sec": 155134967418.24432,
    "active_per_sec": 77567483.70912215,
    "gpu_memory_used_gb": 14.681640625,
    "gpu_memory_available_gb": 15.99169921875,
    "gpu_memory_utilization": 91.8078837287411,
    "cpu_memory_used_gb": 25.279212951660156,
    "cpu_memory_available_gb": 31.419132232666016,
    "cpu_memory_utilization": 80.45802399780388,
    "theoretical_memory_gb": 0.42002648115158087,
    "memory_efficiency": 0.006,
    "cache_hit_rate": 0.0,
    "memory_pool_efficiency": 0.0
  }
]